MANIFEST.in
README.md
VERSION
requirements.txt
setup.py
dvbcss/__init__.py
dvbcss/clock.py
dvbcss/monotonic_time.py
dvbcss/task.py
dvbcss/util.py
dvbcss/protocol/__init__.py
dvbcss/protocol/cii.py
dvbcss/protocol/transformers.py
dvbcss/protocol/ts.py
dvbcss/protocol/wc.py
dvbcss/protocol/client/__init__.py
dvbcss/protocol/client/cii.py
dvbcss/protocol/client/ts.py
dvbcss/protocol/client/wc/__init__.py
dvbcss/protocol/client/wc/algorithm/__init__.py
dvbcss/protocol/client/wc/algorithm/_dispersion.py
dvbcss/protocol/client/wc/algorithm/_filterpredict.py
dvbcss/protocol/client/wc/algorithm/_simple.py
dvbcss/protocol/server/__init__.py
dvbcss/protocol/server/cii.py
dvbcss/protocol/server/ts.py
dvbcss/protocol/server/wc.py
pydvbcss.egg-info/PKG-INFO
pydvbcss.egg-info/SOURCES.txt
pydvbcss.egg-info/dependency_links.txt
pydvbcss.egg-info/requires.txt
pydvbcss.egg-info/top_level.txt
test/__init__.py
test/_useDvbCssUninstalled.py
test/mock_dependent.py
test/mock_time.py
test/test_Clock.py
test/test_Task.py
test/test_all.py
test/test_cii.py
test/test_monotonic_time.py
test/test_ts.py
test/test_wc.py