Metadata-Version: 1.1
Name: pydvbcss
Version: 0.5.2
Summary: pydvbcss is a library implementing DVB "CSS" protocols for Companion Screen Synchronisation.
Home-page: http://github.com/BBC/pydvbcss
Author: Matt Hammond (British Broadcasting Corporation)
Author-email: matt.hammond@bbc.co.uk
License: Apache 2.0
Keywords: dvb companion synchronisation synchronization second-screen protocol
Platform: UNKNOWN
Classifier: Intended Audience :: Developers
Classifier: Intended Audience :: Telecommunications Industry
Classifier: License :: OSI Approved :: Apache Software License
Classifier: Natural Language :: English
Classifier: Operating System :: MacOS :: MacOS X
Classifier: Operating System :: Microsoft :: Windows
Classifier: Operating System :: POSIX :: Linux
Classifier: Programming Language :: Python :: 2.7
Classifier: Topic :: Internet
Classifier: Topic :: Software Development :: Libraries :: Python Modules
Classifier: Topic :: System :: Networking :: Time Synchronization
